libAll/__init__.py
libAll/do_file.py
libAll/funcs.py
libAll/mySql.py
libAll/smtpMail.py
libAll-4.0.dist-info/METADATA
libAll-4.0.dist-info/WHEEL
libAll-4.0.dist-info/top_level.txt
libAll-4.0.dist-info/RECORD
